plutonium/__init__.py
plutonium/bounty.py
plutonium/player.py
plutonium/practice.py
plutonium/server.py
plutonium/top.py
plutonium/assets/headers.py
PlutoniumMCPE-1.0.2.dist-info/LICENSE
PlutoniumMCPE-1.0.2.dist-info/METADATA
PlutoniumMCPE-1.0.2.dist-info/WHEEL
PlutoniumMCPE-1.0.2.dist-info/top_level.txt
PlutoniumMCPE-1.0.2.dist-info/RECORD
