Metadata-Version: 2.1
Name: PlutoniumMCPE
Version: 1.0.2
Summary: Plutonium MCPE Scraper
Home-page: https://github.com/LocheMan/
Author: LocheMan
Keywords: plutonium,mcpe,mcbe
License-File: LICENSE
Requires-Dist: requests
Requires-Dist: beautifulsoup4
